earthcarekit/__init__.py
earthcarekit/calval/__init__.py
earthcarekit/calval/_compare_bsc_ext_lr_depol.py
earthcarekit/calval/_perform_anom_depol_statistics.py
earthcarekit/download/__init__.py
earthcarekit/download/_auth_oads.py
earthcarekit/download/_collection_selection.py
earthcarekit/download/_constants.py
earthcarekit/download/_create_search_requests.py
earthcarekit/download/_eo_collection.py
earthcarekit/download/_eo_parameters.py
earthcarekit/download/_eo_product.py
earthcarekit/download/_eo_search_request.py
earthcarekit/download/_exceptions.py
earthcarekit/download/_organize_data.py
earthcarekit/download/_parse.py
earthcarekit/download/_product_types.py
earthcarekit/download/_remove_old_logs.py
earthcarekit/download/_request.py
earthcarekit/download/_run_downloads.py
earthcarekit/download/_run_search_requests.py
earthcarekit/download/_types.py
earthcarekit/download/_unzip.py
earthcarekit/download/main.py
earthcarekit/plot/__init__.py
earthcarekit/plot/text.py
earthcarekit/plot/color/__init__.py
earthcarekit/plot/color/color.py
earthcarekit/plot/color/color_contrast.py
earthcarekit/plot/color/format_conversion.py
earthcarekit/plot/color/colormap/__init__.py
earthcarekit/plot/color/colormap/atl_simple_classification.py
earthcarekit/plot/color/colormap/atl_target_classification.py
earthcarekit/plot/color/colormap/calipso.py
earthcarekit/plot/color/colormap/calipso_smooth.py
earthcarekit/plot/color/colormap/chiljet.py
earthcarekit/plot/color/colormap/chiljet2.py
earthcarekit/plot/color/colormap/cmap.py
earthcarekit/plot/color/colormap/colormap.py
earthcarekit/plot/color/colormap/cpr_target_classification.py
earthcarekit/plot/color/colormap/doppler_velocity.py
earthcarekit/plot/color/colormap/featuremask.py
earthcarekit/plot/color/colormap/ggplot_like_hcl.py
earthcarekit/plot/color/colormap/hsl.py
earthcarekit/plot/color/colormap/labview.py
earthcarekit/plot/color/colormap/mcm_colormaps.py
earthcarekit/plot/color/colormap/msi_cloud_type.py
earthcarekit-0.13.2.dist-info/licenses/LICENSE
earthcarekit-0.13.2.dist-info/METADATA
earthcarekit-0.13.2.dist-info/WHEEL
earthcarekit-0.13.2.dist-info/entry_points.txt
earthcarekit-0.13.2.dist-info/top_level.txt
earthcarekit-0.13.2.dist-info/RECORD
