Metadata-Version: 2.4
Name: earthcarekit
Version: 0.13.2
Summary: A Python package to simplify working with EarthCARE satellite data.
Author-email: Leonard König <koenig@tropos.de>
License: 
Classifier: Development Status :: 3 - Alpha
Classifier: License :: OSI Approved :: Apache Software License
Classifier: Intended Audience :: Science/Research
Classifier: Intended Audience :: Developers
Classifier: Programming Language :: Python
Classifier: Programming Language :: Python :: 3
Classifier: Programming Language :: Python :: 3.11
Classifier: Programming Language :: Python :: 3.12
Classifier: Programming Language :: Python :: 3.13
Classifier: Programming Language :: Python :: 3.14
Classifier: Topic :: Scientific/Engineering :: Atmospheric Science
Classifier: Topic :: Scientific/Engineering :: Visualization
Classifier: Typing :: Typed
Requires-Python: >=3.11
License-File: LICENSE
Requires-Dist: numpy>=2.3.2
Requires-Dist: pandas>=2.3.1
Requires-Dist: xarray>=2025.7.1
Requires-Dist: matplotlib>=3.10.3
Requires-Dist: plotly>=6.2.0
Requires-Dist: seaborn>=0.13.2
Requires-Dist: cartopy>=0.24.1
Requires-Dist: cmcrameri>=1.9
Requires-Dist: scipy>=1.16.1
Requires-Dist: owslib>=0.34.1
Requires-Dist: jupyterlab>=4.4.5
Requires-Dist: h5netcdf>=1.6.3
Requires-Dist: netcdf4>=1.7.2
Requires-Dist: tomli-w>=1.2.0
Requires-Dist: mkdocstrings-python
Dynamic: license-file
